sphinx_minoo_theme/__init__.py
sphinx_minoo_theme/genindex.html
sphinx_minoo_theme/glossary.html
sphinx_minoo_theme/includes/bottom.html
sphinx_minoo_theme/includes/header.html
sphinx_minoo_theme/includes/sidebar.html
sphinx_minoo_theme/includes/top.html
sphinx_minoo_theme/includes/versions.html
sphinx_minoo_theme/layout.html
sphinx_minoo_theme/page.html
sphinx_minoo_theme/search.html
sphinx_minoo_theme/static/avatar.jpg
sphinx_minoo_theme/static/bootstrap.min.css
sphinx_minoo_theme/static/bootstrap.min.js
sphinx_minoo_theme/static/font-awesome.min.css
sphinx_minoo_theme/static/fonts/FontAwesome.otf
sphinx_minoo_theme/static/fonts/Inconsolata-Bold.ttf
sphinx_minoo_theme/static/fonts/Inconsolata.ttf
sphinx_minoo_theme/static/fonts/Lato-Bold.ttf
sphinx_minoo_theme/static/fonts/Lato-Regular.ttf
sphinx_minoo_theme/static/fonts/RobotoSlab-Bold.ttf
sphinx_minoo_theme/static/fonts/RobotoSlab-Regular.ttf
sphinx_minoo_theme/static/fonts/fontawesome-webfont.eot
sphinx_minoo_theme/static/fonts/fontawesome-webfont.svg
sphinx_minoo_theme/static/fonts/fontawesome-webfont.ttf
sphinx_minoo_theme/static/fonts/fontawesome-webfont.woff
sphinx_minoo_theme/static/fonts/fontawesome-webfont.woff2
sphinx_minoo_theme/static/fonts/glyphicons-halflings-regular.eot
sphinx_minoo_theme/static/fonts/glyphicons-halflings-regular.svg
sphinx_minoo_theme/static/fonts/glyphicons-halflings-regular.ttf
sphinx_minoo_theme/static/fonts/glyphicons-halflings-regular.woff
sphinx_minoo_theme/static/fonts/glyphicons-halflings-regular.woff2
sphinx_minoo_theme/static/minoo-dark.css
sphinx_minoo_theme/static/minoo-ltr.css
sphinx_minoo_theme/static/minoo-rtl.css
sphinx_minoo_theme/static/minoo.js
sphinx_minoo_theme/static/modernizr.min.js
sphinx_minoo_theme/static/pygment-solarized-light.css
sphinx_minoo_theme/theme.conf
sphinx_minoo_theme-1.2.0.dist-info/LICENSE
sphinx_minoo_theme-1.2.0.dist-info/METADATA
sphinx_minoo_theme-1.2.0.dist-info/WHEEL
sphinx_minoo_theme-1.2.0.dist-info/RECORD
