Metadata-Version: 2.3
Name: sphinx_minoo_theme
Version: 1.2.0
Summary: A simple Sphinx theme with RTL language support.
License: MIT
Author: Saeid Darvishghazvini
Author-email: inbox@saeiddrv.com
Requires-Python: >=3.9,<4.0
Classifier: License :: OSI Approved :: MIT License
Classifier: Programming Language :: Python :: 3
Classifier: Programming Language :: Python :: 3.9
Classifier: Programming Language :: Python :: 3.10
Classifier: Programming Language :: Python :: 3.11
Classifier: Programming Language :: Python :: 3.12
Classifier: Programming Language :: Python :: 3.13
Project-URL: Homepage, https://github.com/saeiddrv/SphinxMinooTheme
Project-URL: Repository, https://github.com/saeiddrv/SphinxMinooTheme
